apistar_dynamic/__init__.py
apistar_dynamic/dynamic.py
apistar_dynamic-0.1.0.dist-info/METADATA
apistar_dynamic-0.1.0.dist-info/WHEEL
apistar_dynamic-0.1.0.dist-info/top_level.txt
apistar_dynamic-0.1.0.dist-info/RECORD
